{
  "version": "5",
  "dialect": "mysql",
  "id": "1ccdf681-e7f1-4747-b809-11b58f3156e5",
  "prevId": "00000000-0000-0000-0000-000000000000",
  "tables": {
    "gardu_induk": {
      "name": "gardu_induk",
      "columns": {
        "id": {
          "name": "id",
          "type": "int",
          "primaryKey": false,
          "notNull": true,
          "autoincrement": true
        },
        "nama": {
          "name": "nama",
          "type": "varchar(255)",
          "primaryKey": false,
          "notNull": true,
          "autoincrement": false
        }
      },
      "indexes": {},
      "foreignKeys": {},
      "compositePrimaryKeys": {
        "gardu_induk_id": {
          "name": "gardu_induk_id",
          "columns": [
            "id"
          ]
        }
      },
      "uniqueConstraints": {},
      "checkConstraint": {}
    },
    "manuver": {
      "name": "manuver",
      "columns": {
        "id": {
          "name": "id",
          "type": "int",
          "primaryKey": false,
          "notNull": true,
          "autoincrement": true
        },
        "penyulang_asal_id": {
          "name": "penyulang_asal_id",
          "type": "int",
          "primaryKey": false,
          "notNull": true,
          "autoincrement": false
        },
        "penyulang_tujuan_id": {
          "name": "penyulang_tujuan_id",
          "type": "int",
          "primaryKey": false,
          "notNull": true,
          "autoincrement": false
        },
        "waktu_manuver": {
          "name": "waktu_manuver",
          "type": "datetime",
          "primaryKey": false,
          "notNull": true,
          "autoincrement": false
        },
        "waktu_penormalan": {
          "name": "waktu_penormalan",
          "type": "datetime",
          "primaryKey": false,
          "notNull": false,
          "autoincrement": false
        },
        "beban_ampere_manuver": {
          "name": "beban_ampere_manuver",
          "type": "float",
          "primaryKey": false,
          "notNull": true,
          "autoincrement": false
        },
        "beban_sebelum": {
          "name": "beban_sebelum",
          "type": "float",
          "primaryKey": false,
          "notNull": true,
          "autoincrement": false
        },
        "beban_sesudah": {
          "name": "beban_sesudah",
          "type": "float",
          "primaryKey": false,
          "notNull": false,
          "autoincrement": false
        },
        "keterangan": {
          "name": "keterangan",
          "type": "text",
          "primaryKey": false,
          "notNull": false,
          "autoincrement": false
        },
        "status": {
          "name": "status",
          "type": "enum('AKTIF','NORMAL')",
          "primaryKey": false,
          "notNull": true,
          "autoincrement": false,
          "default": "'AKTIF'"
        }
      },
      "indexes": {},
      "foreignKeys": {},
      "compositePrimaryKeys": {
        "manuver_id": {
          "name": "manuver_id",
          "columns": [
            "id"
          ]
        }
      },
      "uniqueConstraints": {},
      "checkConstraint": {}
    },
    "penyulang": {
      "name": "penyulang",
      "columns": {
        "id": {
          "name": "id",
          "type": "int",
          "primaryKey": false,
          "notNull": true,
          "autoincrement": true
        },
        "nama": {
          "name": "nama",
          "type": "varchar(255)",
          "primaryKey": false,
          "notNull": true,
          "autoincrement": false
        },
        "gardu_induk_id": {
          "name": "gardu_induk_id",
          "type": "int",
          "primaryKey": false,
          "notNull": true,
          "autoincrement": false
        },
        "trf": {
          "name": "trf",
          "type": "varchar(100)",
          "primaryKey": false,
          "notNull": false,
          "autoincrement": false
        },
        "input_arus_siang": {
          "name": "input_arus_siang",
          "type": "float",
          "primaryKey": false,
          "notNull": false,
          "autoincrement": false
        },
        "ulp": {
          "name": "ulp",
          "type": "enum('Bangkalan','Kamal','Blega','Sampang','Pamekasan','Sumenep','Ketapang','Waru','Ambunten')",
          "primaryKey": false,
          "notNull": true,
          "autoincrement": false
        }
      },
      "indexes": {},
      "foreignKeys": {},
      "compositePrimaryKeys": {
        "penyulang_id": {
          "name": "penyulang_id",
          "columns": [
            "id"
          ]
        }
      },
      "uniqueConstraints": {},
      "checkConstraint": {}
    }
  },
  "views": {},
  "_meta": {
    "schemas": {},
    "tables": {},
    "columns": {}
  },
  "internal": {
    "tables": {},
    "indexes": {}
  }
}